MANIFEST.in
README.rst
setup.cfg
setup.py
dunbits/__init__.py
dunbits/api.py
dunbits/create_token.py
dunbits/get_token.py
dunbits/use_token.py
dunbits.egg-info/PKG-INFO
dunbits.egg-info/SOURCES.txt
dunbits.egg-info/dependency_links.txt
dunbits.egg-info/entry_points.txt
dunbits.egg-info/requires.txt
dunbits.egg-info/top_level.txt