Metadata-Version: 1.1
Name: dunbits
Version: 0.0.3
Summary: Dunbits API library
Home-page: https://bitbucket.org/dunbits/dunbits-py
Author: Ferran Pegueroles
Author-email: ferran@pegueorles.com
License: MIT
Keywords: dunbits payments micropayments api development
Platform: UNKNOWN
Classifier: Development Status :: 4 - Beta
Classifier: Intended Audience :: Developers
Classifier: License :: OSI Approved :: MIT License
Classifier: Programming Language :: Python :: 2
Classifier: Programming Language :: Python :: 2.6
Classifier: Programming Language :: Python :: 2.7
Classifier: Programming Language :: Python :: 3
Classifier: Programming Language :: Python :: 3.2
Classifier: Programming Language :: Python :: 3.3
Classifier: Programming Language :: Python :: 3.4
